setup.py
raven_sanitize_openerp/__init__.py
raven_sanitize_openerp.egg-info/PKG-INFO
raven_sanitize_openerp.egg-info/SOURCES.txt
raven_sanitize_openerp.egg-info/dependency_links.txt
raven_sanitize_openerp.egg-info/not-zip-safe
raven_sanitize_openerp.egg-info/requires.txt
raven_sanitize_openerp.egg-info/top_level.txt