Metadata-Version: 1.0
Name: raven-sanitize-openerp
Version: 0.1.1
Summary: Sanitize data for sentry from OpenERP stacktraces
Home-page: http://code.gisce.net/raven-sanitize-openerp
Author: GISCE-TI, SL
Author-email: devel@gisce.net
License: UNKNOWN
Platform: UNKNOWN
Classifier: Intended Audience :: Developers
Classifier: Intended Audience :: System Administrators
Classifier: Operating System :: OS Independent
Classifier: Topic :: Software Development
